[
  {
    "StationNo": "10205",
    "Time": "2023-08-10T00:00:00",
    "EffectiveCapacity": 33550.5,
    "DeadWaterHeight": 110,
    "FullWaterHeight": 170,
    "AccumulatedRainfall": 21.9,
    "InflowTotal": 162.2,
    "OutflowTotal": 162.6
  },
  {
    "StationNo": "10405",
    "Time": "2023-08-10T00:00:00",
    "EffectiveCapacity": 3147.18,
    "DeadWaterHeight": 110,
    "FullWaterHeight": 150,
    "AccumulatedRainfall": 19.5,
    "InflowTotal": 35.66,
    "OutflowTotal": 36.87
  },
  {
    "StationNo": "10802",
    "Time": "2023-08-10T00:00:00",
    "FullWaterHeight": 5.5,
    "AccumulatedRainfall": 0
  },
  {
    "StationNo": "20201",
    "Time": "2023-08-10T00:00:00",
    "EffectiveCapacity": 18866.34,
    "DeadWaterHeight": 1310,
    "FullWaterHeight": 1408,
    "AccumulatedRainfall": 10.5,
    "InflowTotal": 266.469,
    "OutflowTotal": 140.179
  },
  {
    "StationNo": "20508",
    "Time": "2023-08-10T00:00:00",
    "EffectiveCapacity": 692.16,
    "DeadWaterHeight": 427,
    "FullWaterHeight": 448.5,
    "AccumulatedRainfall": 9.5,
    "InflowTotal": -8.66
  },
  {
    "StationNo": "30306",
    "Time": "2023-08-09T07:00:00",
    "EffectiveCapacity": 69,
    "DeadWaterHeight": 50,
    "FullWaterHeight": 60,
    "AccumulatedRainfall": 15,
    "InflowTotal": 0.03,
    "OutflowTotal": 0
  },
  {
    "StationNo": "30401",
    "Time": "2023-08-09T08:00:00",
    "EffectiveCapacity": 1387.5,
    "DeadWaterHeight": 85,
    "FullWaterHeight": 109,
    "AccumulatedRainfall": 14.2,
    "InflowTotal": 37.198,
    "OutflowTotal": 19.1981
  },
  {
    "StationNo": "30403",
    "Time": "2023-08-09T07:00:00",
    "EffectiveCapacity": 229.8,
    "DeadWaterHeight": 11.2,
    "FullWaterHeight": 14.2,
    "AccumulatedRainfall": 47.5,
    "InflowTotal": 53.8334,
    "OutflowTotal": 67.3056
  },
  {
    "StationNo": "30501",
    "Time": "2023-08-09T07:00:00",
    "EffectiveCapacity": 7920.85,
    "DeadWaterHeight": 40,
    "FullWaterHeight": 58.18,
    "AccumulatedRainfall": 12.2,
    "InflowTotal": 137.2,
    "OutflowTotal": 45.2
  },
  {
    "StationNo": "30601",
    "Time": "2023-08-09T08:00:00",
    "EffectiveCapacity": 106.1,
    "DeadWaterHeight": 30.7,
    "FullWaterHeight": 37,
    "AccumulatedRainfall": 33,
    "InflowTotal": 12.6686,
    "OutflowTotal": 0
  },
  {
    "StationNo": "30602",
    "Time": "2023-08-09T08:00:00",
    "EffectiveCapacity": 47.1,
    "DeadWaterHeight": 27.5,
    "FullWaterHeight": 31,
    "AccumulatedRainfall": 36.5,
    "InflowTotal": 3.4443,
    "OutflowTotal": 8.0352
  },
  {
    "StationNo": "31301",
    "Time": "2023-08-10T00:00:00",
    "EffectiveCapacity": 104,
    "DeadWaterHeight": 2,
    "FullWaterHeight": 9,
    "AccumulatedRainfall": 0,
    "InflowTotal": 0,
    "OutflowTotal": 0.205
  },
  {
    "StationNo": "50102",
    "Time": "2023-08-10T00:00:00",
    "EffectiveCapacity": 63.7,
    "DeadWaterHeight": 3,
    "FullWaterHeight": 11,
    "AccumulatedRainfall": 0,
    "InflowTotal": 0,
    "OutflowTotal": 0
  },
  {
    "StationNo": "50103",
    "Time": "2023-08-10T00:00:00",
    "EffectiveCapacity": 18.5,
    "DeadWaterHeight": 0.5,
    "FullWaterHeight": 6.5,
    "AccumulatedRainfall": 0,
    "InflowTotal": 0,
    "OutflowTotal": 0
  },
  {
    "StationNo": "50104",
    "Time": "2023-08-10T00:00:00",
    "EffectiveCapacity": 25.45,
    "DeadWaterHeight": 0,
    "FullWaterHeight": 3,
    "AccumulatedRainfall": 0,
    "InflowTotal": 0,
    "OutflowTotal": 0.033
  },
  {
    "StationNo": "50105",
    "Time": "2023-08-10T00:00:00",
    "EffectiveCapacity": 24,
    "DeadWaterHeight": 4,
    "FullWaterHeight": 12.5,
    "AccumulatedRainfall": 32.5,
    "InflowTotal": 0,
    "OutflowTotal": 0.004
  },
  {
    "StationNo": "50106",
    "Time": "2023-08-10T00:00:00",
    "EffectiveCapacity": 22.84,
    "DeadWaterHeight": 16,
    "FullWaterHeight": 24,
    "AccumulatedRainfall": 13,
    "InflowTotal": 0,
    "OutflowTotal": 0
  },
  {
    "StationNo": "50108",
    "Time": "2023-08-10T00:00:00",
    "EffectiveCapacity": 20.57,
    "DeadWaterHeight": 3,
    "FullWaterHeight": 13.4,
    "AccumulatedRainfall": 0.2,
    "InflowTotal": 0,
    "OutflowTotal": 0
  },
  {
    "StationNo": "50109",
    "Time": "2023-08-10T00:00:00",
    "EffectiveCapacity": 3.54,
    "DeadWaterHeight": 2,
    "FullWaterHeight": 8,
    "AccumulatedRainfall": 32.5,
    "InflowTotal": 0,
    "OutflowTotal": 0.018
  }
]
